CONTRIBUTING.md
MANIFEST.in
README.rst
setup.py
docs/HISTORY.txt
docs/LICENSE.GPL
docs/LICENSE.txt
eea/__init__.py
eea.schema.slate.egg-info/PKG-INFO
eea.schema.slate.egg-info/SOURCES.txt
eea.schema.slate.egg-info/dependency_links.txt
eea.schema.slate.egg-info/entry_points.txt
eea.schema.slate.egg-info/namespace_packages.txt
eea.schema.slate.egg-info/not-zip-safe
eea.schema.slate.egg-info/requires.txt
eea.schema.slate.egg-info/top_level.txt
eea/schema/__init__.py
eea/schema/slate/__init__.py
eea/schema/slate/adapters.py
eea/schema/slate/configure.zcml
eea/schema/slate/editor.py
eea/schema/slate/field.py
eea/schema/slate/handler.py
eea/schema/slate/version.txt
eea/schema/slate/tests/__init__.py
eea/schema/slate/tests/test_doctests.py